{
  "committments":[
  {
    "id": "58cc02fa4b9dc1ebc71a847a",
    "firstName": "Maxwell",
    "lastName": "Harris",
    "phone": "+1 (983) 460-3122",
    "email": "maxwellharris@comvey.com",
    "protest": true,
    "bring": 1,
    "nextLandL": false,
    "duesPayingMember": true,
    "organizer": "Robin Calderon",
    "futureEvents": [
      {
        "id": 1,
        "name": "Trump Tuesday Protest"
      },
      {
        "id": 2,
        "name": "Planet and People First Demonstration"
      }
    ]
  },
  {
    "id": "58cc02fa61dd489a075b25dc",
    "firstName": "Paige",
    "lastName": "Tyson",
    "phone": "+1 (852) 459-3181",
    "email": "paigetyson@comvey.com",
    "protest": true,
    "bring": 0,
    "nextLandL": false,
    "duesPayingMember": false,
    "organizer": "Meyers Conley",
    "futureEvents": [
      {
        "id": 1,
        "name": "Trump Tuesday Protest"
      },
      {
        "id": 2,
        "name": "Planet and People First Demonstration"
      },
      {
        "id": 3,
        "name": "Volunteering"
      }
    ]
  },
  {
    "id": "58cc02fafcf1978cbc11a2b5",
    "firstName": "Erma",
    "lastName": "Stephens",
    "phone": "+1 (975) 497-2526",
    "email": "ermastephens@comvey.com",
    "protest": false,
    "bring": 3,
    "nextLandL": false,
    "duesPayingMember": false,
    "organizer": "Genevieve Hodge",
    "futureEvents": []
  },
  {
    "id": "58cc02fa10ea2399498c60f1",
    "firstName": "Rasmussen",
    "lastName": "Walls",
    "phone": "+1 (949) 422-3076",
    "email": "rasmussenwalls@comvey.com",
    "protest": false,
    "bring": 1,
    "nextLandL": false,
    "duesPayingMember": true,
    "organizer": "Patti Hurley",
    "futureEvents": [
      {
        "id": 1,
        "name": "Trump Tuesday Protest"
      },
      {
        "id": 2,
        "name": "Planet and People First Demonstration"
      }
    ]
  },
  {
    "id": "58cc02faf15340b85ddcaf4f",
    "firstName": "Preston",
    "lastName": "Barron",
    "phone": "+1 (833) 440-3443",
    "email": "prestonbarron@comvey.com",
    "protest": true,
    "bring": 4,
    "nextLandL": false,
    "duesPayingMember": true,
    "organizer": "Lorna Britt",
    "futureEvents": [
      {
        "id": 1,
        "name": "Trump Tuesday Protest"
      },
      {
        "id": 2,
        "name": "Planet and People First Demonstration"
      },
      {
        "id": 3,
        "name": "Volunteering"
      },
      {
        "id": 4,
        "name": "Other"
      }
    ]
  },
  {
    "id": "58cc02fa0b00b6bbabb6168d",
    "firstName": "Melendez",
    "lastName": "Malone",
    "phone": "+1 (876) 533-3991",
    "email": "melendezmalone@comvey.com",
    "protest": false,
    "bring": 3,
    "nextLandL": true,
    "duesPayingMember": true,
    "organizer": "Shelton Olsen",
    "futureEvents": [
      {
        "id": 1,
        "name": "Trump Tuesday Protest"
      },
      {
        "id": 2,
        "name": "Planet and People First Demonstration"
      },
      {
        "id": 3,
        "name": "Volunteering"
      }
    ]
  },
  {
    "id": "58cc02fa76c0d5fadf6ffc00",
    "firstName": "Morrison",
    "lastName": "Moses",
    "phone": "+1 (958) 426-2788",
    "email": "morrisonmoses@comvey.com",
    "protest": false,
    "bring": 4,
    "nextLandL": false,
    "duesPayingMember": false,
    "organizer": "Josefa Wright",
    "futureEvents": [
      {
        "id": 1,
        "name": "Trump Tuesday Protest"
      },
      {
        "id": 2,
        "name": "Planet and People First Demonstration"
      },
      {
        "id": 3,
        "name": "Volunteering"
      },
      {
        "id": 4,
        "name": "Other"
      }
    ]
  },
  {
    "id": "58cc02fa83d6a246797df714",
    "firstName": "Campbell",
    "lastName": "Scott",
    "phone": "+1 (969) 463-3342",
    "email": "campbellscott@comvey.com",
    "protest": true,
    "bring": 3,
    "nextLandL": true,
    "duesPayingMember": true,
    "organizer": "Carrillo Fuller",
    "futureEvents": [
      {
        "id": 1,
        "name": "Trump Tuesday Protest"
      },
      {
        "id": 2,
        "name": "Planet and People First Demonstration"
      },
      {
        "id": 3,
        "name": "Volunteering"
      },
      {
        "id": 4,
        "name": "Other"
      }
    ]
  },
  {
    "id": "58cc02faa27c33317f6334d6",
    "firstName": "Liliana",
    "lastName": "Boyle",
    "phone": "+1 (826) 483-3391",
    "email": "lilianaboyle@comvey.com",
    "protest": false,
    "bring": 2,
    "nextLandL": true,
    "duesPayingMember": false,
    "organizer": "Lindsay Jones",
    "futureEvents": [
      {
        "id": 1,
        "name": "Trump Tuesday Protest"
      },
      {
        "id": 2,
        "name": "Planet and People First Demonstration"
      },
      {
        "id": 3,
        "name": "Volunteering"
      },
      {
        "id": 4,
        "name": "Other"
      }
    ]
  },
  {
    "id": "58cc02fa263a33dd4aeebe3b",
    "firstName": "Marcella",
    "lastName": "Norton",
    "phone": "+1 (911) 535-3041",
    "email": "marcellanorton@comvey.com",
    "protest": false,
    "bring": 2,
    "nextLandL": false,
    "duesPayingMember": false,
    "organizer": "Clemons Foley",
    "futureEvents": []
  },
  {
    "id": "58cc02fab45535706848c5c1",
    "firstName": "Staci",
    "lastName": "Thomas",
    "phone": "+1 (967) 420-3957",
    "email": "stacithomas@comvey.com",
    "protest": false,
    "bring": 1,
    "nextLandL": false,
    "duesPayingMember": true,
    "organizer": "Meyer Charles",
    "futureEvents": [
      {
        "id": 1,
        "name": "Trump Tuesday Protest"
      },
      {
        "id": 2,
        "name": "Planet and People First Demonstration"
      }
    ]
  },
  {
    "id": "58cc02faf2a7ed5c54249420",
    "firstName": "Clayton",
    "lastName": "Norman",
    "phone": "+1 (890) 400-3953",
    "email": "claytonnorman@comvey.com",
    "protest": false,
    "bring": 0,
    "nextLandL": true,
    "duesPayingMember": true,
    "organizer": "Johnston Daniel",
    "futureEvents": [
      {
        "id": 1,
        "name": "Trump Tuesday Protest"
      },
      {
        "id": 2,
        "name": "Planet and People First Demonstration"
      }
    ]
  },
  {
    "id": "58cc02fa78d08cb55d822bde",
    "firstName": "Gutierrez",
    "lastName": "Perez",
    "phone": "+1 (910) 450-3176",
    "email": "gutierrezperez@comvey.com",
    "protest": false,
    "bring": 2,
    "nextLandL": true,
    "duesPayingMember": false,
    "organizer": "Noelle Dunn",
    "futureEvents": [
      {
        "id": 1,
        "name": "Trump Tuesday Protest"
      },
      {
        "id": 2,
        "name": "Planet and People First Demonstration"
      },
      {
        "id": 3,
        "name": "Volunteering"
      },
      {
        "id": 4,
        "name": "Other"
      }
    ]
  },
  {
    "id": "58cc02fa976c6d481ec5a826",
    "firstName": "Frazier",
    "lastName": "Jefferson",
    "phone": "+1 (885) 509-2694",
    "email": "frazierjefferson@comvey.com",
    "protest": false,
    "bring": 3,
    "nextLandL": false,
    "duesPayingMember": false,
    "organizer": "Bowen Snider",
    "futureEvents": [
      {
        "id": 1,
        "name": "Trump Tuesday Protest"
      },
      {
        "id": 2,
        "name": "Planet and People First Demonstration"
      },
      {
        "id": 3,
        "name": "Volunteering"
      }
    ]
  },
  {
    "id": "58cc02fadabb5108e65975e7",
    "firstName": "Chapman",
    "lastName": "Fuentes",
    "phone": "+1 (826) 477-3458",
    "email": "chapmanfuentes@comvey.com",
    "protest": true,
    "bring": 3,
    "nextLandL": false,
    "duesPayingMember": true,
    "organizer": "Alberta Richard",
    "futureEvents": [
      {
        "id": 1,
        "name": "Trump Tuesday Protest"
      }
    ]
  },
  {
    "id": "58cc02fac8b25bdc6f698073",
    "firstName": "Freida",
    "lastName": "Erickson",
    "phone": "+1 (918) 580-2100",
    "email": "freidaerickson@comvey.com",
    "protest": true,
    "bring": 0,
    "nextLandL": true,
    "duesPayingMember": true,
    "organizer": "Crawford Fletcher",
    "futureEvents": [
      {
        "id": 1,
        "name": "Trump Tuesday Protest"
      },
      {
        "id": 2,
        "name": "Planet and People First Demonstration"
      },
      {
        "id": 3,
        "name": "Volunteering"
      }
    ]
  },
  {
    "id": "58cc02faaf61c24621918f88",
    "firstName": "Kerry",
    "lastName": "Cochran",
    "phone": "+1 (854) 575-2756",
    "email": "kerrycochran@comvey.com",
    "protest": true,
    "bring": 0,
    "nextLandL": true,
    "duesPayingMember": false,
    "organizer": "Pam Randall",
    "futureEvents": [
      {
        "id": 1,
        "name": "Trump Tuesday Protest"
      },
      {
        "id": 2,
        "name": "Planet and People First Demonstration"
      },
      {
        "id": 3,
        "name": "Volunteering"
      }
    ]
  },
  {
    "id": "58cc02fa8fdda16ea132b30a",
    "firstName": "Millie",
    "lastName": "Guzman",
    "phone": "+1 (833) 410-2799",
    "email": "millieguzman@comvey.com",
    "protest": false,
    "bring": 3,
    "nextLandL": false,
    "duesPayingMember": false,
    "organizer": "Solomon Sparks",
    "futureEvents": [
      {
        "id": 1,
        "name": "Trump Tuesday Protest"
      }
    ]
  },
  {
    "id": "58cc02fa67f5c5e71e16a52e",
    "firstName": "Ruby",
    "lastName": "Emerson",
    "phone": "+1 (810) 525-3380",
    "email": "rubyemerson@comvey.com",
    "protest": false,
    "bring": 1,
    "nextLandL": false,
    "duesPayingMember": false,
    "organizer": "Natalia Winters",
    "futureEvents": [
      {
        "id": 1,
        "name": "Trump Tuesday Protest"
      },
      {
        "id": 2,
        "name": "Planet and People First Demonstration"
      },
      {
        "id": 3,
        "name": "Volunteering"
      },
      {
        "id": 4,
        "name": "Other"
      }
    ]
  },
  {
    "id": "58cc02fa25f22cbf176df20c",
    "firstName": "Valentine",
    "lastName": "Hunt",
    "phone": "+1 (805) 590-3229",
    "email": "valentinehunt@comvey.com",
    "protest": true,
    "bring": 4,
    "nextLandL": false,
    "duesPayingMember": false,
    "organizer": "Rivas Webster",
    "futureEvents": []
  },
  {
    "id": "58cc02fa70f6a2e12c4f190b",
    "firstName": "Helene",
    "lastName": "Odonnell",
    "phone": "+1 (913) 507-3157",
    "email": "heleneodonnell@comvey.com",
    "protest": false,
    "bring": 4,
    "nextLandL": true,
    "duesPayingMember": true,
    "organizer": "Earline Carver",
    "futureEvents": [
      {
        "id": 1,
        "name": "Trump Tuesday Protest"
      },
      {
        "id": 2,
        "name": "Planet and People First Demonstration"
      },
      {
        "id": 3,
        "name": "Volunteering"
      }
    ]
  },
  {
    "id": "58cc02fab6e8013a451905cd",
    "firstName": "Mccray",
    "lastName": "Rich",
    "phone": "+1 (894) 588-2782",
    "email": "mccrayrich@comvey.com",
    "protest": false,
    "bring": 1,
    "nextLandL": false,
    "duesPayingMember": false,
    "organizer": "Walsh Suarez",
    "futureEvents": []
  },
  {
    "id": "58cc02fab78a6d22f16c1f45",
    "firstName": "Rose",
    "lastName": "Mckay",
    "phone": "+1 (966) 568-2273",
    "email": "rosemckay@comvey.com",
    "protest": true,
    "bring": 1,
    "nextLandL": false,
    "duesPayingMember": true,
    "organizer": "Bette Holland",
    "futureEvents": [
      {
        "id": 1,
        "name": "Trump Tuesday Protest"
      },
      {
        "id": 2,
        "name": "Planet and People First Demonstration"
      },
      {
        "id": 3,
        "name": "Volunteering"
      }
    ]
  },
  {
    "id": "58cc02faf126cebf08ff2708",
    "firstName": "Williamson",
    "lastName": "Carroll",
    "phone": "+1 (960) 559-2991",
    "email": "williamsoncarroll@comvey.com",
    "protest": true,
    "bring": 2,
    "nextLandL": true,
    "duesPayingMember": false,
    "organizer": "Terrell Velez",
    "futureEvents": [
      {
        "id": 1,
        "name": "Trump Tuesday Protest"
      },
      {
        "id": 2,
        "name": "Planet and People First Demonstration"
      }
    ]
  },
  {
    "id": "58cc02faf80bf7f113378e84",
    "firstName": "Letha",
    "lastName": "Waller",
    "phone": "+1 (896) 446-2178",
    "email": "lethawaller@comvey.com",
    "protest": false,
    "bring": 3,
    "nextLandL": true,
    "duesPayingMember": false,
    "organizer": "Sheppard Schwartz",
    "futureEvents": [
      {
        "id": 1,
        "name": "Trump Tuesday Protest"
      }
    ]
  },
  {
    "id": "58cc02fa44c587a136a2da35",
    "firstName": "Vicki",
    "lastName": "Morris",
    "phone": "+1 (866) 552-2064",
    "email": "vickimorris@comvey.com",
    "protest": false,
    "bring": 1,
    "nextLandL": true,
    "duesPayingMember": false,
    "organizer": "Janet Miranda",
    "futureEvents": []
  },
  {
    "id": "58cc02fa1cb05c7fb4cdc625",
    "firstName": "Vaughan",
    "lastName": "Acevedo",
    "phone": "+1 (984) 543-3325",
    "email": "vaughanacevedo@comvey.com",
    "protest": false,
    "bring": 0,
    "nextLandL": true,
    "duesPayingMember": true,
    "organizer": "Alejandra Horton",
    "futureEvents": [
      {
        "id": 1,
        "name": "Trump Tuesday Protest"
      },
      {
        "id": 2,
        "name": "Planet and People First Demonstration"
      }
    ]
  },
  {
    "id": "58cc02fae4affe552dc88165",
    "firstName": "Benita",
    "lastName": "Delgado",
    "phone": "+1 (927) 481-3950",
    "email": "benitadelgado@comvey.com",
    "protest": true,
    "bring": 1,
    "nextLandL": true,
    "duesPayingMember": true,
    "organizer": "Sheree Valencia",
    "futureEvents": [
      {
        "id": 1,
        "name": "Trump Tuesday Protest"
      },
      {
        "id": 2,
        "name": "Planet and People First Demonstration"
      },
      {
        "id": 3,
        "name": "Volunteering"
      }
    ]
  },
  {
    "id": "58cc02fa9eb0bffefa4c6e38",
    "firstName": "Kemp",
    "lastName": "Orr",
    "phone": "+1 (994) 440-2004",
    "email": "kemporr@comvey.com",
    "protest": true,
    "bring": 1,
    "nextLandL": true,
    "duesPayingMember": true,
    "organizer": "Ortega Mccall",
    "futureEvents": [
      {
        "id": 1,
        "name": "Trump Tuesday Protest"
      },
      {
        "id": 2,
        "name": "Planet and People First Demonstration"
      }
    ]
  },
  {
    "id": "58cc02fa7b8df7d3b08aaa84",
    "firstName": "Fleming",
    "lastName": "Cannon",
    "phone": "+1 (916) 421-2466",
    "email": "flemingcannon@comvey.com",
    "protest": false,
    "bring": 0,
    "nextLandL": false,
    "duesPayingMember": false,
    "organizer": "Gould Livingston",
    "futureEvents": [
      {
        "id": 1,
        "name": "Trump Tuesday Protest"
      }
    ]
  }
]
}
